mlx_alt_text/__init__.py
mlx_alt_text/cli.py
mlx_alt_text/constants.py
mlx_alt_text/generator.py
mlx_alt_text-0.1.1.dist-info/METADATA
mlx_alt_text-0.1.1.dist-info/WHEEL
mlx_alt_text-0.1.1.dist-info/entry_points.txt
mlx_alt_text-0.1.1.dist-info/licenses/LICENSE
mlx_alt_text-0.1.1.dist-info/RECORD
