Metadata-Version: 2.4
Name: mlx-alt-text
Version: 0.1.1
Summary: Local-first alt-text generator built on top of MLX-VLM
Project-URL: Source, https://github.com/Jython1415/mlx-alt-text
License-File: LICENSE
Requires-Python: <3.13,>=3.10
Requires-Dist: click>=8.1.8
Requires-Dist: mlx-vlm>=0.0.7
Requires-Dist: mlx>=0.18.1
Requires-Dist: torch>=2.5.1
